mcp_units/__init__.py
mcp_units/server.py
mcp_units/converters/__init__.py
mcp_units/converters/temperature.py
mcp_units/converters/volume.py
mcp_units/converters/weight.py
mcp_units/utils/__init__.py
mcp_units/utils/validation.py
mcp_units-0.3.3.dist-info/METADATA
mcp_units-0.3.3.dist-info/WHEEL
mcp_units-0.3.3.dist-info/entry_points.txt
mcp_units-0.3.3.dist-info/RECORD
