Metadata-Version: 2.4
Name: mcp-units
Version: 0.3.3
Summary: An MCP server for cooking unit conversions
Author-email: Diamantis Sellis <sellisd@gmail.com>
License-Expression: MIT
Keywords: conversion,cooking,mcp,units
Classifier: Intended Audience :: Developers
Classifier: License :: OSI Approved :: MIT License
Classifier: Operating System :: OS Independent
Classifier: Programming Language :: Python :: 3
Classifier: Programming Language :: Python :: 3.11
Classifier: Topic :: Software Development :: Libraries
Classifier: Topic :: Utilities
Requires-Python: >=3.11
Requires-Dist: jsonschema>=4.0.0
Requires-Dist: mcp==1.15.0
Requires-Dist: pytest-asyncio>=0.23.0
Requires-Dist: pytest>=7.4.4
Requires-Dist: ruff>=0.11.5
Provides-Extra: dev
Requires-Dist: pytest-asyncio>=0.23.0; extra == 'dev'
Requires-Dist: pytest>=7.0.0; extra == 'dev'
